vptq/__init__.py
vptq/__main__.py
vptq/app.py
vptq/app_gpu.py
vptq/app_utils.py
vptq/libvptq.so
vptq/layers/__init__.py
vptq/layers/model_base.py
vptq/layers/utils.py
vptq/layers/vqlinear.py
vptq/ops/__init__.py
vptq/ops/quant_gemm.py
vptq/tests/test_generation.py
vptq/tools/__init__.py
vptq/tools/pre_process.py
vptq/tools/hessian/__init__.py
vptq/utils/__init__.py
vptq/utils/pack.py
vptq-0.0.5.post1.dist-info/LICENSE
vptq-0.0.5.post1.dist-info/METADATA
vptq-0.0.5.post1.dist-info/WHEEL
vptq-0.0.5.post1.dist-info/top_level.txt
vptq-0.0.5.post1.dist-info/RECORD
