Metadata-Version: 2.2
Name: vptq
Version: 0.0.5.post1
Summary: VPTQ (Vector Post-Training Quantization) is a novel Post-Training Quantization method.
Author: Wang Yang, Wen JiCheng
Author-email: Ying Cao <lcy.seso@gmail.com>, Jicheng Wen <wejoincy@gmail.com>, Yang Wang <wyatuestc@gmail.com>
Project-URL: Homepage, https://github.com/microsoft/VPTQ
Project-URL: Issues, https://github.com/microsoft/VPTQ/issues
Classifier: Programming Language :: Python :: 3
Classifier: License :: OSI Approved :: MIT License
Classifier: Operating System :: OS Independent
Classifier: Topic :: Software Development :: Libraries
Requires-Python: >=3.8
License-File: LICENSE
Requires-Dist: torch>=2.3.0
Requires-Dist: datasets
Requires-Dist: transformers>=4.45
Requires-Dist: safetensors
Requires-Dist: psutil
Requires-Dist: accelerate
Requires-Dist: gradio
Requires-Dist: plotly==5.9.0
Requires-Dist: pynvml
Requires-Dist: tqdm
Requires-Dist: sentence_transformers
Dynamic: author
Dynamic: requires-python
